{
    "model": {
        "selectAllText": {
            "_type": "TextualDisplay",
            "textSpans": [{
                "_type": "TextSpan",
                "text": "Select all"
            }]
        },
        "operations": [{
            "action": {
                "text": "Delete"
            },
            "confirmationContent": {
                "title": {
                    "_type": "TextualDisplay",
                    "textSpans": [{
                        "_type": "TextSpan",
                        "text": "Delete draft(s)"
                    }]
                },
                "content": {
                    "_type": "TextualDisplay",
                    "textSpans": [{
                        "_type": "TextSpan",
                        "text": "Are you sure you want to delete the selected draft(s)?"
                    }]
                },
                "confirm": {
                    "text": "Delete",
                    "type": "PRIMARY",
                    "action": {
                        "type": "OPERATION"
                    }
                },
                "cancel": {
                    "text": "Cancel",
                    "type": "SECONDARY",
                    "action": {
                        "type": "OPERATION"
                    }
                },
                "close": {
                    "text": "Close",
                    "type": "DEFAULT",
                    "action": {
                        "type": "OPERATION"
                    },
                    "accessibilityText": "close dialogue"
                }
            },
            "message": {
                "title": {
                    "textSpans": [{
                        "text": "We weren’t able to delete these items right now. Please try again later."
                    }]
                }
            }
        }]
    }

}
